{
  "comment_count": 2,
  "comments": [
    {
      "id": "4124",
      "author": "brilynn",
      "author_url": "http://www.jumboempanadas.blogspot.com",
      "date": "2007-08-31 18:22:35",
      "content": "Those look awesome!  I can see why they disappeared so quickly.",
      "parent": "0",
      "gravatar_hash": "e42534c281521378126d3812811f5658"
    },
    {
      "id": "4125",
      "author": "brilynn",
      "author_url": "http://www.jumboempanadas.blogspot.com",
      "date": "2007-08-31 18:23:42",
      "content": "Those look awesome!  I can see why they disappeared so quickly.",
      "parent": "0",
      "gravatar_hash": "e42534c281521378126d3812811f5658"
    }
  ]
}