{
  "comment_count": 11,
  "comments": [
    {
      "id": "2427",
      "author": "arugulove",
      "author_url": "http://arugulove.wordpress.com",
      "date": "2009-05-28 12:19:21",
      "content": "This looks incredible.  Thanks!",
      "parent": "0",
      "gravatar_hash": "253d1978cdae80b623ebb342e1426589"
    },
    {
      "id": "2428",
      "author": "Michael Natkin",
      "author_url": "",
      "date": "2009-05-28 12:55:57",
      "content": "You could add arugula :)!",
      "parent": "0",
      "gravatar_hash": "a52f8f9146768ce0dc36a285e4c4d38d"
    },
    {
      "id": "2429",
      "author": "lisaiscooking",
      "author_url": "http://lisaiscooking.blogspot.com/",
      "date": "2009-05-28 14:50:43",
      "content": "What a simple and delicious thing! This is a perfect start to an easy summer meal.",
      "parent": "0",
      "gravatar_hash": "561295eae7a0ea547c538ab03aca58f2"
    },
    {
      "id": "2430",
      "author": "Tofu Mom",
      "author_url": "http://tofu-n-sproutz.blogspot.com/",
      "date": "2009-05-29 00:10:27",
      "content": "This looks freaking amazing. I have some fantastic grape-seed oil from Eastern Washington and I'm thinking it'd go great here. Obviously you know I'm trying to figure out something instead of the cheese, not sure what yet. *thinking* But this looks way too awesome not to try a variation of!!!",
      "parent": "0",
      "gravatar_hash": "1a0b4a32e20aa0dec8b1491f2bea1ad6"
    },
    {
      "id": "2431",
      "author": "Michael Natkin",
      "author_url": "",
      "date": "2009-05-29 20:42:17",
      "content": "Tofu Mom - Does the grape-seed oil have a flavor or is it neutral tasting?\nI'm curious what you come up with for a veganized version of this dish.",
      "parent": "0",
      "gravatar_hash": "a52f8f9146768ce0dc36a285e4c4d38d"
    },
    {
      "id": "2432",
      "author": "Daily Spud",
      "author_url": "http://www.thedailyspud.com",
      "date": "2009-06-04 06:33:13",
      "content": "This is great - I have goats cheese, I have grapes, I have chives with flowers, I have fresh oregano, I will have this dish :) I haven't (that I can think of) tried sauteeing fruit before, but I was served some sauteed strawberries as a side dish lately and definitely want to give it a try...",
      "parent": "0",
      "gravatar_hash": "574ac8e528f96dc53d671e1d6f19b0e0"
    },
    {
      "id": "2433",
      "author": "Michael Natkin",
      "author_url": "",
      "date": "2009-06-04 06:57:22",
      "content": "Nice! Let me know how you like it.",
      "parent": "0",
      "gravatar_hash": "a52f8f9146768ce0dc36a285e4c4d38d"
    },
    {
      "id": "2434",
      "author": "alana",
      "author_url": "",
      "date": "2009-06-23 13:07:39",
      "content": "I made it -- easy, refreshing, delicate flavours. my partner was really impressed. the texture on the grapes is really nice after stir frying for 30 seconds. colours were great. it's always so exciting to come up with a new easy little thing that is a special and still simple alternative to my usual standby of tomatoes and fresh mozz.",
      "parent": "0",
      "gravatar_hash": "faa6971ac0bacc731c8be8a644f591c9"
    },
    {
      "id": "52632",
      "author": "Venera@Veggykitchen.com",
      "author_url": "http://www.veggykitchen.com",
      "date": "2012-09-18 22:34:45",
      "content": "Easy and delicious! This is what I like to do to make something special out of ordinary dinner.\nThanks!",
      "parent": "0",
      "gravatar_hash": "fa24f1035ae22ade4cb815b45f6c4678"
    },
    {
      "id": "168332",
      "author": "Anjali",
      "author_url": "",
      "date": "2013-07-01 20:31:20",
      "content": "Looks really good !!  However I cannot get chives with florets easily. What do you suggest I replace this with?",
      "parent": "0",
      "gravatar_hash": "1fcefa93af06ae1eef89007f60f98fa7"
    },
    {
      "id": "168800",
      "author": "Michael Natkin",
      "author_url": "https://herbivoracious.com",
      "date": "2013-07-02 12:50:05",
      "content": "I'd just skip the flowers and use regular fresh chives.",
      "parent": "168332",
      "gravatar_hash": "a52f8f9146768ce0dc36a285e4c4d38d"
    }
  ]
}