{
  "comment_count": 3,
  "comments": [
    {
      "id": "3743",
      "author": "Eric LeVine",
      "author_url": "http://www.cellartracker.com",
      "date": "2008-02-11 00:13:49",
      "content": "Mmm, these were fantastic. It was a pleasure to have you over. Fantastic cooking!",
      "parent": "0",
      "gravatar_hash": "e8876d51fc531c6979a21cba12630549"
    },
    {
      "id": "3744",
      "author": "Barbara Stewart",
      "author_url": "http://www.synchronicitycoaching.com",
      "date": "2008-02-11 17:25:04",
      "content": "Thank you for the Valentine's Day recipe Michael. We will definitely be doing this one on Thursday.\nHow would these be with the raspberry compote on the inside? I might even try that.",
      "parent": "0",
      "gravatar_hash": "35a0844a632079f9c80145caa1fbbe0e"
    },
    {
      "id": "3745",
      "author": "Michael Natkin",
      "author_url": "",
      "date": "2008-02-11 19:47:20",
      "content": "Thanks Eric & Barbara! I think the compote on the inside would be dandy.",
      "parent": "0",
      "gravatar_hash": "a52f8f9146768ce0dc36a285e4c4d38d"
    }
  ]
}